PyRingD/PyRingD.py
PyRingD-1.1.1.dist-info/LICENCE
PyRingD-1.1.1.dist-info/METADATA
PyRingD-1.1.1.dist-info/WHEEL
PyRingD-1.1.1.dist-info/top_level.txt
PyRingD-1.1.1.dist-info/RECORD
